{
  "global": {
    "Primary Colour": {
      "value": "#ff7b7b",
      "type": "color",
      "description": "use this colour for primary actions"
    },
    "Text Colour": {
      "value": "#181818",
      "type": "color",
      "description": "Use this colour instead of black or #00 in text or anywhere required\n"
    },
    "Base Text": {
      "value": {
        "fontFamily": "Epilogue"
      },
      "type": "typography"
    }
  },
  "$themes": [],
  "$metadata": {
    "tokenSetOrder": [
      "global"
    ]
  }
}